{
    "nodes": [
        {
            "id": 0,
            "channel": 7,
            "sf": 7,
            "transmission_p": 20,
            "x": 3113,
            "y": 4992,
            "z": 0,
            "type": 0,
            "assigned_node": -1,
            "following": -1
        },
        {
            "id": 1,
            "channel": 4,
            "sf": 7,
            "transmission_p": 20,
            "x": 2878,
            "y": -5550,
            "z": 0,
            "type": 0,
            "assigned_node": -1,
            "following": -1
        },
        {
            "id": 2,
            "channel": 6,
            "sf": 7,
            "transmission_p": 20,
            "x": 3930,
            "y": 4176,
            "z": 0,
            "type": 0,
            "assigned_node": -1,
            "following": -1
        },
        {
            "id": 3,
            "channel": 4,
            "sf": 7,
            "transmission_p": 20,
            "x": 2605,
            "y": 5559,
            "z": 0,
            "type": 0,
            "assigned_node": -1,
            "following": -1
        },
        {
            "id": 4,
            "channel": 0,
            "sf": 7,
            "transmission_p": 20,
            "x": 1116,
            "y": 5954,
            "z": 0,
            "type": 0,
            "assigned_node": -1,
            "following": -1
        },
        {
            "id": 5,
            "channel": 4,
            "sf": 7,
            "transmission_p": 20,
            "x": 413,
            "y": 6294,
            "z": 0,
            "type": 0,
            "assigned_node": -1,
            "following": -1
        },
        {
            "id": 6,
            "channel": 7,
            "sf": 7,
            "transmission_p": 20,
            "x": 3898,
            "y": 4978,
            "z": 0,
            "type": 0,
            "assigned_node": -1,
            "following": -1
        },
        {
            "id": 7,
            "channel": 0,
            "sf": 7,
            "transmission_p": 20,
            "x": 4551,
            "y": 4618,
            "z": 0,
            "type": 0,
            "assigned_node": -1,
            "following": -1
        },
        {
            "id": 8,
            "channel": 3,
            "sf": 7,
            "transmission_p": 20,
            "x": 4039,
            "y": 5212,
            "z": 0,
            "type": 0,
            "assigned_node": -1,
            "following": -1
        },
        {
            "id": 9,
            "channel": 7,
            "sf": 7,
            "transmission_p": 20,
            "x": 2826,
            "y": -5372,
            "z": 0,
            "type": 0,
            "assigned_node": -1,
            "following": -1
        },
        {
            "id": 10,
            "channel": 0,
            "sf": 7,
            "transmission_p": 20,
            "x": 3586,
            "y": 5842,
            "z": 0,
            "type": 0,
            "assigned_node": -1,
            "following": -1
        },
        {
            "id": 11,
            "channel": 2,
            "sf": 7,
            "transmission_p": 20,
            "x": 3789,
            "y": 4612,
            "z": 0,
            "type": 0,
            "assigned_node": -1,
            "following": -1
        },
        {
            "id": 12,
            "channel": 5,
            "sf": 7,
            "transmission_p": 20,
            "x": 3503,
            "y": -6000,
            "z": 0,
            "type": 0,
            "assigned_node": -1,
            "following": -1
        },
        {
            "id": 13,
            "channel": 2,
            "sf": 7,
            "transmission_p": 20,
            "x": 4740,
            "y": 3740,
            "z": 0,
            "type": 0,
            "assigned_node": -1,
            "following": -1
        },
        {
            "id": 14,
            "channel": 1,
            "sf": 7,
            "transmission_p": 20,
            "x": 324,
            "y": 7044,
            "z": 0,
            "type": 0,
            "assigned_node": -1,
            "following": -1
        },
        {
            "id": 15,
            "channel": 2,
            "sf": 7,
            "transmission_p": 20,
            "x": 4564,
            "y": 5406,
            "z": 0,
            "type": 0,
            "assigned_node": -1,
            "following": -1
        },
        {
            "id": 16,
            "channel": 3,
            "sf": 7,
            "transmission_p": 20,
            "x": 5969,
            "y": -552,
            "z": 0,
            "type": 0,
            "assigned_node": -1,
            "following": -1
        },
        {
            "id": 17,
            "channel": 0,
            "sf": 7,
            "transmission_p": 20,
            "x": 5659,
            "y": 1303,
            "z": 0,
            "type": 0,
            "assigned_node": -1,
            "following": -1
        },
        {
            "id": 18,
            "channel": 1,
            "sf": 7,
            "transmission_p": 20,
            "x": 3215,
            "y": -6719,
            "z": 0,
            "type": 0,
            "assigned_node": -1,
            "following": -1
        },
        {
            "id": 19,
            "channel": 2,
            "sf": 7,
            "transmission_p": 20,
            "x": 4891,
            "y": 4478,
            "z": 0,
            "type": 0,
            "assigned_node": -1,
            "following": -1
        },
        {
            "id": 20,
            "channel": 2,
            "sf": 7,
            "transmission_p": 20,
            "x": 3616,
            "y": 5208,
            "z": 0,
            "type": 0,
            "assigned_node": -1,
            "following": -1
        },
        {
            "id": 21,
            "channel": 8,
            "sf": 7,
            "transmission_p": 20,
            "x": -6249,
            "y": 1154,
            "z": 0,
            "type": 0,
            "assigned_node": -1,
            "following": -1
        },
        {
            "id": 22,
            "channel": 3,
            "sf": 7,
            "transmission_p": 20,
            "x": 6159,
            "y": -765,
            "z": 0,
            "type": 0,
            "assigned_node": -1,
            "following": -1
        },
        {
            "id": 23,
            "channel": 7,
            "sf": 7,
            "transmission_p": 20,
            "x": -6745,
            "y": 540,
            "z": 0,
            "type": 0,
            "assigned_node": -1,
            "following": -1
        },
        {
            "id": 24,
            "channel": 7,
            "sf": 7,
            "transmission_p": 20,
            "x": 3280,
            "y": -7476,
            "z": 0,
            "type": 0,
            "assigned_node": -1,
            "following": -1
        },
        {
            "id": 25,
            "channel": 1,
            "sf": 7,
            "transmission_p": 20,
            "x": 6136,
            "y": 1894,
            "z": 0,
            "type": 0,
            "assigned_node": -1,
            "following": -1
        },
        {
            "id": 26,
            "channel": 4,
            "sf": 7,
            "transmission_p": 20,
            "x": 2474,
            "y": -6227,
            "z": 0,
            "type": 0,
            "assigned_node": -1,
            "following": -1
        },
        {
            "id": 27,
            "channel": 0,
            "sf": 7,
            "transmission_p": 20,
            "x": 5958,
            "y": 334,
            "z": 0,
            "type": 0,
            "assigned_node": -1,
            "following": -1
        },
        {
            "id": 28,
            "channel": 2,
            "sf": 7,
            "transmission_p": 20,
            "x": 2153,
            "y": -5737,
            "z": 0,
            "type": 0,
            "assigned_node": -1,
            "following": -1
        },
        {
            "id": 29,
            "channel": 5,
            "sf": 7,
            "transmission_p": 20,
            "x": 3122,
            "y": 4976,
            "z": 0,
            "type": 0,
            "assigned_node": -1,
            "following": -1
        },
        {
            "id": 30,
            "channel": 8,
            "sf": 7,
            "transmission_p": 20,
            "x": 6361,
            "y": 125,
            "z": 0,
            "type": 0,
            "assigned_node": -1,
            "following": -1
        },
        {
            "id": 31,
            "channel": 8,
            "sf": 7,
            "transmission_p": 20,
            "x": -7502,
            "y": 607,
            "z": 0,
            "type": 0,
            "assigned_node": -1,
            "following": -1
        },
        {
            "id": 32,
            "channel": 1,
            "sf": 7,
            "transmission_p": 20,
            "x": 6009,
            "y": 523,
            "z": 0,
            "type": 0,
            "assigned_node": -1,
            "following": -1
        },
        {
            "id": 33,
            "channel": 1,
            "sf": 7,
            "transmission_p": 20,
            "x": 5225,
            "y": 5152,
            "z": 0,
            "type": 0,
            "assigned_node": -1,
            "following": -1
        },
        {
            "id": 34,
            "channel": 1,
            "sf": 7,
            "transmission_p": 20,
            "x": 5921,
            "y": -488,
            "z": 0,
            "type": 0,
            "assigned_node": -1,
            "following": -1
        },
        {
            "id": 35,
            "channel": 0,
            "sf": 7,
            "transmission_p": 20,
            "x": 6424,
            "y": 1204,
            "z": 0,
            "type": 0,
            "assigned_node": -1,
            "following": -1
        },
        {
            "id": 36,
            "channel": 5,
            "sf": 7,
            "transmission_p": 20,
            "x": 5450,
            "y": 3462,
            "z": 0,
            "type": 0,
            "assigned_node": -1,
            "following": -1
        },
        {
            "id": 37,
            "channel": 8,
            "sf": 7,
            "transmission_p": 20,
            "x": 3220,
            "y": -6073,
            "z": 0,
            "type": 0,
            "assigned_node": -1,
            "following": -1
        },
        {
            "id": 38,
            "channel": 7,
            "sf": 7,
            "transmission_p": 20,
            "x": 2936,
            "y": -5811,
            "z": 0,
            "type": 0,
            "assigned_node": -1,
            "following": -1
        },
        {
            "id": 39,
            "channel": 1,
            "sf": 7,
            "transmission_p": 20,
            "x": 5642,
            "y": -1544,
            "z": 0,
            "type": 0,
            "assigned_node": -1,
            "following": -1
        },
        {
            "id": 40,
            "channel": 4,
            "sf": 7,
            "transmission_p": 20,
            "x": 1786,
            "y": 5544,
            "z": 0,
            "type": 0,
            "assigned_node": -1,
            "following": -1
        },
        {
            "id": 41,
            "channel": 2,
            "sf": 7,
            "transmission_p": 20,
            "x": 5344,
            "y": 5481,
            "z": 0,
            "type": 0,
            "assigned_node": -1,
            "following": -1
        },
        {
            "id": 42,
            "channel": 7,
            "sf": 7,
            "transmission_p": 20,
            "x": 5250,
            "y": 5925,
            "z": 0,
            "type": 0,
            "assigned_node": -1,
            "following": -1
        },
        {
            "id": 43,
            "channel": 2,
            "sf": 7,
            "transmission_p": 20,
            "x": 6373,
            "y": 1026,
            "z": 0,
            "type": 0,
            "assigned_node": -1,
            "following": -1
        },
        {
            "id": 44,
            "channel": 6,
            "sf": 7,
            "transmission_p": 20,
            "x": -7533,
            "y": 504,
            "z": 0,
            "type": 0,
            "assigned_node": -1,
            "following": -1
        },
        {
            "id": 45,
            "channel": 7,
            "sf": 7,
            "transmission_p": 20,
            "x": 4630,
            "y": 3364,
            "z": 0,
            "type": 0,
            "assigned_node": -1,
            "following": -1
        },
        {
            "id": 46,
            "channel": 3,
            "sf": 7,
            "transmission_p": 20,
            "x": 5398,
            "y": 6663,
            "z": 0,
            "type": 0,
            "assigned_node": -1,
            "following": -1
        },
        {
            "id": 47,
            "channel": 8,
            "sf": 7,
            "transmission_p": 20,
            "x": 5795,
            "y": 2070,
            "z": 0,
            "type": 0,
            "assigned_node": -1,
            "following": -1
        },
        {
            "id": 48,
            "channel": 2,
            "sf": 7,
            "transmission_p": 20,
            "x": 2179,
            "y": 5236,
            "z": 0,
            "type": 0,
            "assigned_node": -1,
            "following": -1
        },
        {
            "id": 49,
            "channel": 0,
            "sf": 7,
            "transmission_p": 20,
            "x": -7820,
            "y": -81,
            "z": 0,
            "type": 0,
            "assigned_node": -1,
            "following": -1
        },
        {
            "id": 50,
            "channel": 1,
            "sf": 7,
            "transmission_p": 20,
            "x": 6364,
            "y": 2626,
            "z": 0,
            "type": 0,
            "assigned_node": -1,
            "following": -1
        },
        {
            "id": 51,
            "channel": 1,
            "sf": 7,
            "transmission_p": 20,
            "x": 3063,
            "y": -6722,
            "z": 0,
            "type": 0,
            "assigned_node": -1,
            "following": -1
        },
        {
            "id": 52,
            "channel": 7,
            "sf": 7,
            "transmission_p": 20,
            "x": 4776,
            "y": 4105,
            "z": 0,
            "type": 0,
            "assigned_node": -1,
            "following": -1
        },
        {
            "id": 53,
            "channel": 6,
            "sf": 7,
            "transmission_p": 20,
            "x": 6046,
            "y": 6261,
            "z": 0,
            "type": 0,
            "assigned_node": -1,
            "following": -1
        },
        {
            "id": 54,
            "channel": 0,
            "sf": 7,
            "transmission_p": 20,
            "x": -2107,
            "y": -5235,
            "z": 0,
            "type": 0,
            "assigned_node": -1,
            "following": -1
        },
        {
            "id": 55,
            "channel": 3,
            "sf": 7,
            "transmission_p": 20,
            "x": 1793,
            "y": 6298,
            "z": 0,
            "type": 0,
            "assigned_node": -1,
            "following": -1
        },
        {
            "id": 56,
            "channel": 5,
            "sf": 7,
            "transmission_p": 20,
            "x": 1877,
            "y": 6304,
            "z": 0,
            "type": 0,
            "assigned_node": -1,
            "following": -1
        },
        {
            "id": 57,
            "channel": 4,
            "sf": 7,
            "transmission_p": 20,
            "x": 6898,
            "y": 1807,
            "z": 0,
            "type": 0,
            "assigned_node": -1,
            "following": -1
        },
        {
            "id": 58,
            "channel": 6,
            "sf": 7,
            "transmission_p": 20,
            "x": 4508,
            "y": 4355,
            "z": 0,
            "type": 0,
            "assigned_node": -1,
            "following": -1
        },
        {
            "id": 59,
            "channel": 8,
            "sf": 7,
            "transmission_p": 20,
            "x": 2923,
            "y": -6570,
            "z": 0,
            "type": 0,
            "assigned_node": -1,
            "following": -1
        },
        {
            "id": 60,
            "channel": 5,
            "sf": 7,
            "transmission_p": 20,
            "x": -2027,
            "y": -6014,
            "z": 0,
            "type": 0,
            "assigned_node": -1,
            "following": -1
        },
        {
            "id": 61,
            "channel": 1,
            "sf": 7,
            "transmission_p": 20,
            "x": 1173,
            "y": 6657,
            "z": 0,
            "type": 0,
            "assigned_node": -1,
            "following": -1
        },
        {
            "id": 62,
            "channel": 3,
            "sf": 7,
            "transmission_p": 20,
            "x": 2550,
            "y": 6345,
            "z": 0,
            "type": 0,
            "assigned_node": -1,
            "following": -1
        },
        {
            "id": 63,
            "channel": 1,
            "sf": 7,
            "transmission_p": 20,
            "x": 6192,
            "y": 2734,
            "z": 0,
            "type": 0,
            "assigned_node": -1,
            "following": -1
        },
        {
            "id": 64,
            "channel": 6,
            "sf": 7,
            "transmission_p": 20,
            "x": 3056,
            "y": -5211,
            "z": 0,
            "type": 0,
            "assigned_node": -1,
            "following": -1
        },
        {
            "id": 65,
            "channel": 4,
            "sf": 7,
            "transmission_p": 20,
            "x": -8451,
            "y": -493,
            "z": 0,
            "type": 0,
            "assigned_node": -1,
            "following": -1
        },
        {
            "id": 66,
            "channel": 8,
            "sf": 7,
            "transmission_p": 20,
            "x": 6306,
            "y": -26,
            "z": 0,
            "type": 0,
            "assigned_node": -1,
            "following": -1
        },
        {
            "id": 67,
            "channel": 4,
            "sf": 7,
            "transmission_p": 20,
            "x": 2855,
            "y": 4823,
            "z": 0,
            "type": 0,
            "assigned_node": -1,
            "following": -1
        },
        {
            "id": 68,
            "channel": 7,
            "sf": 7,
            "transmission_p": 20,
            "x": 4242,
            "y": 4774,
            "z": 0,
            "type": 0,
            "assigned_node": -1,
            "following": -1
        },
        {
            "id": 69,
            "channel": 8,
            "sf": 7,
            "transmission_p": 20,
            "x": -7760,
            "y": 1224,
            "z": 0,
            "type": 0,
            "assigned_node": -1,
            "following": -1
        },
        {
            "id": 70,
            "channel": 6,
            "sf": 7,
            "transmission_p": 20,
            "x": 3821,
            "y": -6827,
            "z": 0,
            "type": 0,
            "assigned_node": -1,
            "following": -1
        },
        {
            "id": 71,
            "channel": 0,
            "sf": 7,
            "transmission_p": 20,
            "x": 3174,
            "y": 5758,
            "z": 0,
            "type": 0,
            "assigned_node": -1,
            "following": -1
        },
        {
            "id": 72,
            "channel": 7,
            "sf": 7,
            "transmission_p": 20,
            "x": 5257,
            "y": -861,
            "z": 0,
            "type": 0,
            "assigned_node": -1,
            "following": -1
        },
        {
            "id": 73,
            "channel": 2,
            "sf": 7,
            "transmission_p": 20,
            "x": 3028,
            "y": -4432,
            "z": 0,
            "type": 0,
            "assigned_node": -1,
            "following": -1
        },
        {
            "id": 74,
            "channel": 3,
            "sf": 7,
            "transmission_p": 20,
            "x": 2362,
            "y": 5044,
            "z": 0,
            "type": 0,
            "assigned_node": -1,
            "following": -1
        },
        {
            "id": 75,
            "channel": 3,
            "sf": 7,
            "transmission_p": 20,
            "x": -1325,
            "y": -5297,
            "z": 0,
            "type": 0,
            "assigned_node": -1,
            "following": -1
        },
        {
            "id": 76,
            "channel": 8,
            "sf": 7,
            "transmission_p": 20,
            "x": 2371,
            "y": -4750,
            "z": 0,
            "type": 0,
            "assigned_node": -1,
            "following": -1
        },
        {
            "id": 77,
            "channel": 7,
            "sf": 7,
            "transmission_p": 20,
            "x": 4012,
            "y": 3979,
            "z": 0,
            "type": 0,
            "assigned_node": -1,
            "following": -1
        },
        {
            "id": 78,
            "channel": 2,
            "sf": 7,
            "transmission_p": 20,
            "x": 4912,
            "y": 2634,
            "z": 0,
            "type": 0,
            "assigned_node": -1,
            "following": -1
        },
        {
            "id": 79,
            "channel": 3,
            "sf": 7,
            "transmission_p": 20,
            "x": 2323,
            "y": -4708,
            "z": 0,
            "type": 0,
            "assigned_node": -1,
            "following": -1
        },
        {
            "id": 80,
            "channel": 8,
            "sf": 7,
            "transmission_p": 20,
            "x": 5291,
            "y": -14,
            "z": 0,
            "type": 0,
            "assigned_node": -1,
            "following": -1
        },
        {
            "id": 81,
            "channel": 6,
            "sf": 7,
            "transmission_p": 20,
            "x": 3257,
            "y": 4164,
            "z": 0,
            "type": 0,
            "assigned_node": -1,
            "following": -1
        },
        {
            "id": 82,
            "channel": 1,
            "sf": 7,
            "transmission_p": 20,
            "x": 4025,
            "y": 3498,
            "z": 0,
            "type": 0,
            "assigned_node": -1,
            "following": -1
        },
        {
            "id": 83,
            "channel": 8,
            "sf": 7,
            "transmission_p": 20,
            "x": 5506,
            "y": -1183,
            "z": 0,
            "type": 0,
            "assigned_node": -1,
            "following": -1
        },
        {
            "id": 84,
            "channel": 5,
            "sf": 7,
            "transmission_p": 20,
            "x": 3247,
            "y": 4549,
            "z": 0,
            "type": 0,
            "assigned_node": -1,
            "following": -1
        },
        {
            "id": 85,
            "channel": 4,
            "sf": 7,
            "transmission_p": 20,
            "x": 1425,
            "y": 5267,
            "z": 0,
            "type": 0,
            "assigned_node": -1,
            "following": -1
        },
        {
            "id": 86,
            "channel": 4,
            "sf": 7,
            "transmission_p": 20,
            "x": -5479,
            "y": 979,
            "z": 0,
            "type": 0,
            "assigned_node": -1,
            "following": -1
        },
        {
            "id": 87,
            "channel": 4,
            "sf": 7,
            "transmission_p": 20,
            "x": 5265,
            "y": 657,
            "z": 0,
            "type": 0,
            "assigned_node": -1,
            "following": -1
        },
        {
            "id": 88,
            "channel": 0,
            "sf": 7,
            "transmission_p": 20,
            "x": -4408,
            "y": -3543,
            "z": 0,
            "type": 0,
            "assigned_node": -1,
            "following": -1
        },
        {
            "id": 89,
            "channel": 6,
            "sf": 7,
            "transmission_p": 20,
            "x": 2253,
            "y": -5087,
            "z": 0,
            "type": 0,
            "assigned_node": -1,
            "following": -1
        }
    ],
    "gateways": [
        {
            "id": 1,
            "x": 3754,
            "y": 3754,
            "z": 0
        },
        {
            "id": 2,
            "x": -3754,
            "y": 3754,
            "z": 0
        },
        {
            "id": 3,
            "x": 0,
            "y": -5308,
            "z": 0
        }
    ],
    "load": 1.0,
    "life_time": 1000000,
    "case": "LoraWAN 3 gateways",
    "level": 1,
    "prt": "Aloha",
    "rate_prd": 1.0,
    "max_sf": 7.0
}