{
    "nodes": [
        {
            "id": 0,
            "channel": 0,
            "sf": 7,
            "transmission_p": 14,
            "x": 33202,
            "y": 43931,
            "z": 134,
            "type": 0,
            "assigned_node": -1,
            "following": -1
        },
        {
            "id": 1,
            "channel": 1,
            "sf": 7,
            "transmission_p": 14,
            "x": 65279,
            "y": 44973,
            "z": 146,
            "type": 0,
            "assigned_node": -1,
            "following": -1
        },
        {
            "id": 2,
            "channel": 2,
            "sf": 7,
            "transmission_p": 14,
            "x": 49291,
            "y": 34603,
            "z": 132,
            "type": 0,
            "assigned_node": -1,
            "following": -1
        },
        {
            "id": 3,
            "channel": 3,
            "sf": 7,
            "transmission_p": 14,
            "x": 67938,
            "y": 50936,
            "z": 103,
            "type": 0,
            "assigned_node": -1,
            "following": -1
        },
        {
            "id": 4,
            "channel": 4,
            "sf": 7,
            "transmission_p": 14,
            "x": 62567,
            "y": 37204,
            "z": 122,
            "type": 0,
            "assigned_node": -1,
            "following": -1
        },
        {
            "id": 5,
            "channel": 5,
            "sf": 7,
            "transmission_p": 14,
            "x": 47036,
            "y": 35233,
            "z": 104,
            "type": 0,
            "assigned_node": -1,
            "following": -1
        },
        {
            "id": 6,
            "channel": 6,
            "sf": 7,
            "transmission_p": 14,
            "x": 46854,
            "y": 63191,
            "z": 108,
            "type": 0,
            "assigned_node": -1,
            "following": -1
        },
        {
            "id": 7,
            "channel": 7,
            "sf": 7,
            "transmission_p": 14,
            "x": 45875,
            "y": 32807,
            "z": 129,
            "type": 0,
            "assigned_node": -1,
            "following": -1
        },
        {
            "id": 8,
            "channel": 8,
            "sf": 7,
            "transmission_p": 14,
            "x": 42224,
            "y": 36497,
            "z": 100,
            "type": 0,
            "assigned_node": -1,
            "following": -1
        },
        {
            "id": 9,
            "channel": 0,
            "sf": 7,
            "transmission_p": 14,
            "x": 59280,
            "y": 61986,
            "z": 132,
            "type": 0,
            "assigned_node": -1,
            "following": -1
        },
        {
            "id": 10,
            "channel": 1,
            "sf": 7,
            "transmission_p": 14,
            "x": 36095,
            "y": 48480,
            "z": 119,
            "type": 0,
            "assigned_node": -1,
            "following": -1
        },
        {
            "id": 11,
            "channel": 2,
            "sf": 7,
            "transmission_p": 14,
            "x": 39127,
            "y": 37190,
            "z": 144,
            "type": 0,
            "assigned_node": -1,
            "following": -1
        },
        {
            "id": 12,
            "channel": 3,
            "sf": 7,
            "transmission_p": 14,
            "x": 36397,
            "y": 49234,
            "z": 105,
            "type": 0,
            "assigned_node": -1,
            "following": -1
        },
        {
            "id": 13,
            "channel": 4,
            "sf": 7,
            "transmission_p": 14,
            "x": 36485,
            "y": 52789,
            "z": 107,
            "type": 0,
            "assigned_node": -1,
            "following": -1
        },
        {
            "id": 14,
            "channel": 5,
            "sf": 7,
            "transmission_p": 14,
            "x": 52234,
            "y": 65237,
            "z": 113,
            "type": 0,
            "assigned_node": -1,
            "following": -1
        },
        {
            "id": 15,
            "channel": 6,
            "sf": 7,
            "transmission_p": 14,
            "x": 65430,
            "y": 58237,
            "z": 105,
            "type": 0,
            "assigned_node": -1,
            "following": -1
        },
        {
            "id": 16,
            "channel": 7,
            "sf": 7,
            "transmission_p": 14,
            "x": 63549,
            "y": 47570,
            "z": 140,
            "type": 0,
            "assigned_node": -1,
            "following": -1
        },
        {
            "id": 17,
            "channel": 8,
            "sf": 7,
            "transmission_p": 14,
            "x": 42111,
            "y": 64278,
            "z": 142,
            "type": 0,
            "assigned_node": -1,
            "following": -1
        },
        {
            "id": 18,
            "channel": 0,
            "sf": 7,
            "transmission_p": 14,
            "x": 40835,
            "y": 36346,
            "z": 113,
            "type": 0,
            "assigned_node": -1,
            "following": -1
        },
        {
            "id": 19,
            "channel": 1,
            "sf": 7,
            "transmission_p": 14,
            "x": 53038,
            "y": 36151,
            "z": 117,
            "type": 0,
            "assigned_node": -1,
            "following": -1
        },
        {
            "id": 20,
            "channel": 2,
            "sf": 7,
            "transmission_p": 14,
            "x": 63226,
            "y": 42467,
            "z": 144,
            "type": 0,
            "assigned_node": -1,
            "following": -1
        },
        {
            "id": 21,
            "channel": 3,
            "sf": 7,
            "transmission_p": 14,
            "x": 46431,
            "y": 67304,
            "z": 139,
            "type": 0,
            "assigned_node": -1,
            "following": -1
        },
        {
            "id": 22,
            "channel": 4,
            "sf": 7,
            "transmission_p": 14,
            "x": 35800,
            "y": 60752,
            "z": 103,
            "type": 0,
            "assigned_node": -1,
            "following": -1
        },
        {
            "id": 23,
            "channel": 5,
            "sf": 7,
            "transmission_p": 14,
            "x": 39984,
            "y": 63132,
            "z": 148,
            "type": 0,
            "assigned_node": -1,
            "following": -1
        },
        {
            "id": 24,
            "channel": 6,
            "sf": 7,
            "transmission_p": 14,
            "x": 57426,
            "y": 33890,
            "z": 137,
            "type": 0,
            "assigned_node": -1,
            "following": -1
        },
        {
            "id": 25,
            "channel": 7,
            "sf": 7,
            "transmission_p": 14,
            "x": 64985,
            "y": 47563,
            "z": 121,
            "type": 0,
            "assigned_node": -1,
            "following": -1
        },
        {
            "id": 26,
            "channel": 8,
            "sf": 7,
            "transmission_p": 14,
            "x": 46634,
            "y": 64551,
            "z": 148,
            "type": 0,
            "assigned_node": -1,
            "following": -1
        },
        {
            "id": 27,
            "channel": 0,
            "sf": 7,
            "transmission_p": 14,
            "x": 52420,
            "y": 33720,
            "z": 115,
            "type": 0,
            "assigned_node": -1,
            "following": -1
        },
        {
            "id": 28,
            "channel": 1,
            "sf": 7,
            "transmission_p": 14,
            "x": 60286,
            "y": 61107,
            "z": 119,
            "type": 0,
            "assigned_node": -1,
            "following": -1
        },
        {
            "id": 29,
            "channel": 2,
            "sf": 7,
            "transmission_p": 14,
            "x": 39516,
            "y": 37825,
            "z": 119,
            "type": 0,
            "assigned_node": -1,
            "following": -1
        },
        {
            "id": 30,
            "channel": 3,
            "sf": 7,
            "transmission_p": 14,
            "x": 38101,
            "y": 58795,
            "z": 141,
            "type": 0,
            "assigned_node": -1,
            "following": -1
        },
        {
            "id": 31,
            "channel": 4,
            "sf": 7,
            "transmission_p": 14,
            "x": 38241,
            "y": 60958,
            "z": 132,
            "type": 0,
            "assigned_node": -1,
            "following": -1
        },
        {
            "id": 32,
            "channel": 5,
            "sf": 7,
            "transmission_p": 14,
            "x": 43941,
            "y": 36419,
            "z": 146,
            "type": 0,
            "assigned_node": -1,
            "following": -1
        },
        {
            "id": 33,
            "channel": 6,
            "sf": 7,
            "transmission_p": 14,
            "x": 34646,
            "y": 58990,
            "z": 101,
            "type": 0,
            "assigned_node": -1,
            "following": -1
        },
        {
            "id": 34,
            "channel": 7,
            "sf": 7,
            "transmission_p": 14,
            "x": 54824,
            "y": 35341,
            "z": 102,
            "type": 0,
            "assigned_node": -1,
            "following": -1
        },
        {
            "id": 35,
            "channel": 8,
            "sf": 7,
            "transmission_p": 14,
            "x": 64441,
            "y": 53607,
            "z": 144,
            "type": 0,
            "assigned_node": -1,
            "following": -1
        },
        {
            "id": 36,
            "channel": 0,
            "sf": 7,
            "transmission_p": 14,
            "x": 66399,
            "y": 53159,
            "z": 117,
            "type": 0,
            "assigned_node": -1,
            "following": -1
        },
        {
            "id": 37,
            "channel": 1,
            "sf": 7,
            "transmission_p": 14,
            "x": 60031,
            "y": 40533,
            "z": 128,
            "type": 0,
            "assigned_node": -1,
            "following": -1
        },
        {
            "id": 38,
            "channel": 2,
            "sf": 7,
            "transmission_p": 14,
            "x": 37241,
            "y": 39544,
            "z": 103,
            "type": 0,
            "assigned_node": -1,
            "following": -1
        },
        {
            "id": 39,
            "channel": 3,
            "sf": 7,
            "transmission_p": 14,
            "x": 63777,
            "y": 44706,
            "z": 111,
            "type": 0,
            "assigned_node": -1,
            "following": -1
        },
        {
            "id": 40,
            "channel": 4,
            "sf": 7,
            "transmission_p": 14,
            "x": 49984,
            "y": 43166,
            "z": 118,
            "type": 0,
            "assigned_node": -1,
            "following": -1
        },
        {
            "id": 41,
            "channel": 5,
            "sf": 7,
            "transmission_p": 14,
            "x": 57547,
            "y": 57104,
            "z": 118,
            "type": 0,
            "assigned_node": -1,
            "following": -1
        },
        {
            "id": 42,
            "channel": 6,
            "sf": 7,
            "transmission_p": 14,
            "x": 39384,
            "y": 54583,
            "z": 128,
            "type": 0,
            "assigned_node": -1,
            "following": -1
        },
        {
            "id": 43,
            "channel": 7,
            "sf": 7,
            "transmission_p": 14,
            "x": 46450,
            "y": 58739,
            "z": 135,
            "type": 0,
            "assigned_node": -1,
            "following": -1
        },
        {
            "id": 44,
            "channel": 8,
            "sf": 7,
            "transmission_p": 14,
            "x": 58598,
            "y": 49262,
            "z": 117,
            "type": 0,
            "assigned_node": -1,
            "following": -1
        },
        {
            "id": 45,
            "channel": 0,
            "sf": 7,
            "transmission_p": 14,
            "x": 59865,
            "y": 49589,
            "z": 140,
            "type": 0,
            "assigned_node": -1,
            "following": -1
        },
        {
            "id": 46,
            "channel": 1,
            "sf": 7,
            "transmission_p": 14,
            "x": 56959,
            "y": 56601,
            "z": 104,
            "type": 0,
            "assigned_node": -1,
            "following": -1
        },
        {
            "id": 47,
            "channel": 2,
            "sf": 7,
            "transmission_p": 14,
            "x": 56355,
            "y": 46464,
            "z": 138,
            "type": 0,
            "assigned_node": -1,
            "following": -1
        },
        {
            "id": 48,
            "channel": 3,
            "sf": 7,
            "transmission_p": 14,
            "x": 53360,
            "y": 56204,
            "z": 141,
            "type": 0,
            "assigned_node": -1,
            "following": -1
        },
        {
            "id": 49,
            "channel": 4,
            "sf": 7,
            "transmission_p": 14,
            "x": 60293,
            "y": 51417,
            "z": 129,
            "type": 0,
            "assigned_node": -1,
            "following": -1
        }
    ],
    "gateways": [
        {
            "id": 1,
            "x": 54060,
            "y": 51383,
            "z": 41
        },
        {
            "id": 2,
            "x": 45518,
            "y": 46029,
            "z": 41
        },
        {
            "id": 3,
            "x": 53252,
            "y": 52685,
            "z": 41
        }
    ],
    "load": 1.0,
    "life_time": 100000,
    "case": "LoraWAN 3 gateways"
}